signadot_sdk/__init__.py
signadot_sdk/api_client.py
signadot_sdk/configuration.py
signadot_sdk/rest.py
signadot_sdk/api/__init__.py
signadot_sdk/api/cluster_api.py
signadot_sdk/api/route_groups_api.py
signadot_sdk/api/sandboxes_api.py
signadot_sdk/models/__init__.py
signadot_sdk/models/cluster.py
signadot_sdk/models/cluster_operator.py
signadot_sdk/models/cluster_token.py
signadot_sdk/models/cluster_token_status.py
signadot_sdk/models/empty_response.py
signadot_sdk/models/error_response.py
signadot_sdk/models/route_group.py
signadot_sdk/models/route_group_endpoint.py
signadot_sdk/models/route_group_match.py
signadot_sdk/models/route_group_match_label.py
signadot_sdk/models/route_group_spec.py
signadot_sdk/models/route_group_spec_endpoint.py
signadot_sdk/models/route_group_status.py
signadot_sdk/models/sandbox.py
signadot_sdk/models/sandbox_custom_patch.py
signadot_sdk/models/sandbox_customizations.py
signadot_sdk/models/sandbox_default_route_group.py
signadot_sdk/models/sandbox_endpoint.py
signadot_sdk/models/sandbox_env_value_from.py
signadot_sdk/models/sandbox_env_value_from_fork.py
signadot_sdk/models/sandbox_env_value_from_resource.py
signadot_sdk/models/sandbox_env_var.py
signadot_sdk/models/sandbox_fork.py
signadot_sdk/models/sandbox_fork_endpoint.py
signadot_sdk/models/sandbox_fork_of.py
signadot_sdk/models/sandbox_host_endpoint.py
signadot_sdk/models/sandbox_image.py
signadot_sdk/models/sandbox_readiness.py
signadot_sdk/models/sandbox_resource.py
signadot_sdk/models/sandbox_spec.py
signadot_sdk/models/sandbox_ttl.py
signadot_sdk_snapshot/__init__.py
signadot_sdk_snapshot/api_client.py
signadot_sdk_snapshot/configuration.py
signadot_sdk_snapshot/rest.py
signadot_sdk_snapshot/api/__init__.py
signadot_sdk_snapshot/api/cluster_api.py
signadot_sdk_snapshot/api/resource_plugins_api.py
signadot_sdk_snapshot/api/route_groups_api.py
signadot_sdk_snapshot/api/sandboxes_api.py
signadot_sdk_snapshot/models/__init__.py
signadot_sdk_snapshot/models/apierrs_response.py
signadot_sdk_snapshot-0.3.7.dev10.dist-info/METADATA
signadot_sdk_snapshot-0.3.7.dev10.dist-info/WHEEL
signadot_sdk_snapshot-0.3.7.dev10.dist-info/top_level.txt
signadot_sdk_snapshot-0.3.7.dev10.dist-info/RECORD
